AUTHORS.md
CHANGES.md
LICENSE
MANIFEST.in
README.md
requirements.txt
setup.py
examples/README.md
examples/dot/README.md
examples/dot/requirements.txt
path_and_address/__init__.py
path_and_address/parsing.py
path_and_address/validation.py
path_and_address.egg-info/PKG-INFO
path_and_address.egg-info/SOURCES.txt
path_and_address.egg-info/dependency_links.txt
path_and_address.egg-info/top_level.txt